[{"name":"daniel","position":"doctor","username":"daniel","password":"1234567","id":1,"loginStatus":false},{"name":"jill","position":"nurse","username":"jill","password":"222333","id":2,"loginStatus":false},{"name":"holly","position":"receptionist","username":"holly","password":"098765","id":3,"loginStatus":false},{"name":"andre","position":"admin","username":"andre","password":"1112223","id":4,"loginStatus":false},{"name":"boy","position":"office boy","username":"boy","password":"54321","id":5,"loginStatus":false}]